cntracer.cp39-win32.pyd
cntracer-2.1.1.dist-info/LICENSE
cntracer-2.1.1.dist-info/METADATA
cntracer-2.1.1.dist-info/WHEEL
cntracer-2.1.1.dist-info/top_level.txt
cntracer-2.1.1.dist-info/RECORD
