Metadata-Version: 2.1
Name: cntracer
Version: 2.1.1
Summary: utils for xw
Home-page: https://www.openerpenext.com/
Author: xw odoo
Author-email: 1161752300@qq.com
Requires-Python: >=3.7
License-File: LICENSE
